adderlib/__init__.py
adderlib/adder.py
adderlib/channels.py
adderlib/devices.py
adderlib/presets.py
adderlib/urlhandlers.py
adderlib/users.py
adderlib-1.0.3.dist-info/LICENSE
adderlib-1.0.3.dist-info/METADATA
adderlib-1.0.3.dist-info/WHEEL
adderlib-1.0.3.dist-info/top_level.txt
adderlib-1.0.3.dist-info/RECORD
