Metadata-Version: 2.1
Name: adderlib
Version: 1.0.3
Summary: Python wrapper for the Adder API, for use with Adderlink KVM systems
Home-page: https://adderlib.readthedocs.io/
Download-URL: https://github.com/mjiggidy/adderlib/
Author: Michael Jordan
Author-email: michael@glowingpixel.com
License: GNU General Public License v3 or later (GPLv3+)
Classifier: License :: OSI Approved :: GNU General Public License v3 or later (GPLv3+)
Classifier: Development Status :: 5 - Production/Stable
Classifier: Intended Audience :: System Administrators
Classifier: Topic :: Multimedia
Classifier: Topic :: Internet
Classifier: Topic :: Utilities
Classifier: Operating System :: OS Independent
Classifier: Programming Language :: Python :: 3
Classifier: Programming Language :: Python :: 3.9
Classifier: Natural Language :: English
Requires-Python: >=3.7
License-File: LICENSE
Requires-Dist: requests
Requires-Dist: xmltodict (==0.12.0)
